odoo/addons/crm_lead_search_archive/README.rst
odoo/addons/crm_lead_search_archive/__init__.py
odoo/addons/crm_lead_search_archive/__manifest__.py
odoo/addons/crm_lead_search_archive/i18n/crm_lead_search_archive.pot
odoo/addons/crm_lead_search_archive/i18n/fr.po
odoo/addons/crm_lead_search_archive/readme/CONTRIBUTORS.rst
odoo/addons/crm_lead_search_archive/readme/DESCRIPTION.rst
odoo/addons/crm_lead_search_archive/static/description/icon.png
odoo/addons/crm_lead_search_archive/static/description/index.html
odoo/addons/crm_lead_search_archive/views/crm_lead_view.xml
odoo14_addon_crm_lead_search_archive-14.0.1.0.1.dist-info/METADATA
odoo14_addon_crm_lead_search_archive-14.0.1.0.1.dist-info/WHEEL
odoo14_addon_crm_lead_search_archive-14.0.1.0.1.dist-info/top_level.txt
odoo14_addon_crm_lead_search_archive-14.0.1.0.1.dist-info/RECORD
